hotrecharge/HRConfig.py
hotrecharge/HotRecharge.py
hotrecharge/HotRechargeExcHandler.py
hotrecharge/HotRechargeException.py
hotrecharge/__init__.py
hotrecharge/__main__.py
hot_recharge-4.0.0.dist-info/LICENSE
hot_recharge-4.0.0.dist-info/METADATA
hot_recharge-4.0.0.dist-info/WHEEL
hot_recharge-4.0.0.dist-info/top_level.txt
hot_recharge-4.0.0.dist-info/RECORD
