Metadata-Version: 2.1
Name: hot-recharge
Version: 4.0.0
Summary: perform hot-recharge services with hot-recharge library programmatically
Home-page: https://github.com/DonnC/Hot-Recharge-ZW
Author: Donald Chinhuru
Author-email: donychinhuru@gmail.com
License: MIT
Platform: UNKNOWN
Classifier: License :: OSI Approved :: MIT License
Classifier: Programming Language :: Python :: 3
Classifier: Operating System :: OS Independent
License-File: LICENSE
